parrot/OCRLib.py
parrot/__init__.py
robotframework_parrot_ocrlib-1.0.3.dist-info/LICENSE
robotframework_parrot_ocrlib-1.0.3.dist-info/METADATA
robotframework_parrot_ocrlib-1.0.3.dist-info/WHEEL
robotframework_parrot_ocrlib-1.0.3.dist-info/top_level.txt
robotframework_parrot_ocrlib-1.0.3.dist-info/RECORD
