Metadata-Version: 2.1
Name: robotframework-parrot-ocrlib
Version: 1.0.3
Summary: OCR Library to recognize text within a digital image
Home-page: https://github.com/zilogic-systems/parrot
Author: Zilogic Systems
Author-email: code@zilogic.com
Classifier: Programming Language :: Python :: 3
Requires-Python: >=3.6
License-File: LICENSE
Requires-Dist: pillow
Requires-Dist: pytesseract
Requires-Dist: numpy
Requires-Dist: robotframework
